masked_split/__init__.py
masked_split/masked_split.py
masked_split-0.0.2.dist-info/METADATA
masked_split-0.0.2.dist-info/WHEEL
masked_split-0.0.2.dist-info/licenses/LICENSE
masked_split-0.0.2.dist-info/RECORD
